klazify_api/__init__.py
klazify_api/client.py
klazify-0.4.dist-info/METADATA
klazify-0.4.dist-info/WHEEL
klazify-0.4.dist-info/top_level.txt
klazify-0.4.dist-info/RECORD
