Metadata-Version: 2.1
Name: klazify
Version: 0.4
Summary: The most accurate Content Classification API. All-in-one domain data source
Home-page: https://github.com/Zyla-Labs/pypi-klazify-api
Author: Klazify
Author-email: hello@klazify.com
Keywords: Get Website Logos api,Brand Imagery api,We Categorize the Web,api for website,api key for website,logo api,banking logo api,company logo api,api key website,api of website,best api for website,create an api for a website,create an api for your website,Website Category API, Website Logo API,logo api,URL logo api,Webshrinker,classifies a site into a category,brandfetch,url categorization,url category check api,website category lookup,web categories,url classification dataset
